{
  "paper_id": "W3197287220",
  "task": "knowledge-enhanced recommendation",
  "input": "user-item interaction graph and item knowledge graph",
  "output": "ranked list of items per user",
  "backbone": "collaborative graph convolution network (CGCN)",
  "loss": "BPR loss + self-supervised mutual information maximization",
  "key_idea": "jointly model item-item interactions from user-item graph and entity connectivity from KG, with self-supervised learning to align interaction-aware and knowledge-aware preferences",
  "datasets": [
    "Amazon-Book",
    "Last-FM"
  ],
  "metrics": [
    "Recall",
    "NDCG"
  ],
  "name": null,
  "problem": null,
  "method": null,
  "baselines": []
}